flogin/__init__.py
flogin/__main__.py
flogin/_types.py
flogin/caching.py
flogin/conditions.py
flogin/default_events.py
flogin/errors.py
flogin/plugin.py
flogin/py.typed
flogin/query.py
flogin/search_handler.py
flogin/settings.py
flogin/utils.py
flogin/flow/__init__.py
flogin/flow/api.py
flogin/flow/base.py
flogin/flow/enums.py
flogin/flow/fuzzy_search.py
flogin/flow/plugin_metadata.py
flogin/flow/settings.py
flogin/jsonrpc/__init__.py
flogin/jsonrpc/base_object.py
flogin/jsonrpc/client.py
flogin/jsonrpc/errors.py
flogin/jsonrpc/requests.py
flogin/jsonrpc/responses.py
flogin/jsonrpc/results.py
flogin/testing/__init__.py
flogin/testing/filler.py
flogin/testing/plugin_tester.py
flogin-1.1.0.dist-info/METADATA
flogin-1.1.0.dist-info/WHEEL
flogin-1.1.0.dist-info/top_level.txt
flogin-1.1.0.dist-info/RECORD
