Metadata-Version: 2.1
Name: flogin
Version: 1.1.0
Summary: A Python wrapper for Flow Launcher's v2 python api
Author: cibere
Project-URL: Documentation, https://flogin.readthedocs.io/en/latest/
Project-URL: Issue tracker, https://github.com/cibere/flogin/issues
Classifier: License :: OSI Approved :: MIT License
Classifier: Intended Audience :: Developers
Classifier: Natural Language :: English
Classifier: Operating System :: Microsoft :: Windows :: Windows 10
Classifier: Operating System :: Microsoft :: Windows :: Windows 11
Classifier: Programming Language :: Python :: 3.11
Classifier: Programming Language :: Python :: 3.12
Classifier: Programming Language :: Python :: 3.13
Classifier: Topic :: Software Development :: Libraries
Classifier: Topic :: Software Development :: Libraries :: Python Modules
Classifier: Topic :: Utilities
Classifier: Typing :: Typed
Classifier: Programming Language :: Python :: Implementation :: CPython
Requires-Python: >=3.11
Requires-Dist: aioconsole==0.8.1
Provides-Extra: docs
Requires-Dist: sphinx<9.0.0,>=7.0.0; extra == "docs"
Requires-Dist: furo==2024.8.6; extra == "docs"
Requires-Dist: sphinx-autodoc-typehints<4.0.0,>=1.25.0; extra == "docs"
Requires-Dist: sphinx-toolbox<4.0,>=3.5; extra == "docs"
Requires-Dist: sphinxcontrib-trio==1.1.2; extra == "docs"
Requires-Dist: sphinx-copybutton==0.5.2; extra == "docs"
Provides-Extra: tests
Requires-Dist: pytest==8.3.4; extra == "tests"
Requires-Dist: pytest-asyncio==0.25.1; extra == "tests"
